main.py
fetchers/news_api.py
fetchers/openlibrary_api.py
fetchers/wikipedia_function.py
processing/config.py
processing/csv_exporter.py
processing/pdf_exporter.py
processing/ui.py
processing/utils.py
sourcefolio-1.0.10.dist-info/licenses/LICENSE
sourcefolio-1.0.10.dist-info/METADATA
sourcefolio-1.0.10.dist-info/WHEEL
sourcefolio-1.0.10.dist-info/entry_points.txt
sourcefolio-1.0.10.dist-info/top_level.txt
sourcefolio-1.0.10.dist-info/RECORD
