Metadata-Version: 2.4
Name: sourcefolio
Version: 1.0.10
Summary: A CLI tool to automate research by fetching data from multiple sources and exporting to PDF/CSV.
Author-email: shakeelsaga <shakeelmohammedofficial@gmail.com>
Project-URL: Homepage, https://github.com/shakeelsaga/SourceFolio
Project-URL: Issues, https://github.com/shakeelsaga/SourceFolio/issues
Project-URL: icon, https://cdn.jsdelivr.net/gh/shakeelsaga/SourceFolio@main/.assets/SourceFolio-Logo.png
Classifier: Programming Language :: Python :: 3
Classifier: License :: OSI Approved :: MIT License
Classifier: Operating System :: OS Independent
Classifier: Topic :: Utilities
Classifier: Environment :: Console
Requires-Python: >=3.8
License-File: LICENSE
Requires-Dist: rich
Requires-Dist: inquirerpy
Requires-Dist: typer[all]
Requires-Dist: wikipedia
Requires-Dist: requests
Requires-Dist: python-dotenv
Requires-Dist: reportlab
Requires-Dist: beautifulsoup4
Dynamic: license-file
